{
  "project_info": {
    "project_number": "608401918959",
    "firebase_url": "https://reactnativefirebaseex.firebaseio.com",
    "project_id": "reactnativefirebaseex",
    "storage_bucket": "reactnativefirebaseex.appspot.com"
  },
  "client": [
    {
      "client_info": {
        "mobilesdk_app_id": "1:608401918959:android:fa132ea72280c25b",
        "android_client_info": {
          "package_name": "com.firebaseuploadexample"
        }
      },
      "oauth_client": [
        {
          "client_id": "608401918959-vjg5dqsanvj9rr30v37noheoc7796ddr.apps.googleusercontent.com",
          "client_type": 3
        }
      ],
      "api_key": [
        {
          "current_key": "AIzaSyBZxeRVFwiI4lkMqa3YztO_MIB012m7d2U"
        }
      ],
      "services": {
        "analytics_service": {
          "status": 1
        },
        "appinvite_service": {
          "status": 1,
          "other_platform_oauth_client": []
        },
        "ads_service": {
          "status": 2
        }
      }
    }
  ],
  "configuration_version": "1"
}